Desafio_image/__init__.py
Desafio_image/processo/__init__.py
Desafio_image/processo/combinacao.py
Desafio_image/processo/transformacao.py
Desafio_image/utilidades/__init__.py
Desafio_image/utilidades/io.py
Desafio_image/utilidades/plot.py
desafio_image-0.0.2.dist-info/METADATA
desafio_image-0.0.2.dist-info/WHEEL
desafio_image-0.0.2.dist-info/top_level.txt
desafio_image-0.0.2.dist-info/RECORD
